pdfautonup/__init__.py
pdfautonup/__main__.py
pdfautonup/errors.py
pdfautonup/geometry.py
pdfautonup/options.py
pdfautonup/paper.py
pdfautonup/pdfbackend/__init__.py
pdfautonup/pdfbackend/pymupdf.py
pdfautonup/pdfbackend/pypdf.py
pdfautonup-1.12.3.dist-info/licenses/AUTHORS
pdfautonup-1.12.3.dist-info/licenses/LICENSE
pdfautonup-1.12.3.dist-info/METADATA
pdfautonup-1.12.3.dist-info/WHEEL
pdfautonup-1.12.3.dist-info/entry_points.txt
pdfautonup-1.12.3.dist-info/top_level.txt
pdfautonup-1.12.3.dist-info/zip-safe
pdfautonup-1.12.3.dist-info/RECORD
