Metadata-Version: 2.4
Name: pdfautonup
Version: 1.12.3
Summary: Convert PDF files to 'n-up' PDF files, guessing the output layout.
Home-page: http://framagit.org/spalax/pdfautonup
Author: Louis Paternault
Author-email: spalax@gresille.org
License: AGPLv3 or any later version
Project-URL: Documentation, http://pdfautonup.readthedocs.io
Project-URL: Source, https://framagit.org/spalax/pdfautonup
Project-URL: Tracker, https://framagit.org/spalax/pdfautonup/issues
Keywords: pdf nup
Classifier: Development Status :: 5 - Production/Stable
Classifier: Environment :: Console
Classifier: License :: OSI Approved :: GNU Affero General Public License v3 or later (AGPLv3+)
Classifier: Intended Audience :: End Users/Desktop
Classifier: Intended Audience :: Education
Classifier: Operating System :: OS Independent
Classifier: Programming Language :: Python
Classifier: Programming Language :: Python :: 3
Classifier: Programming Language :: Python :: 3.10
Classifier: Programming Language :: Python :: 3.11
Classifier: Programming Language :: Python :: 3.12
Classifier: Programming Language :: Python :: 3.13
Classifier: Programming Language :: Python :: 3.14
Classifier: Topic :: Printing
Requires-Python: <4,>=3.10
License-File: LICENSE
License-File: AUTHORS
Requires-Dist: pypdf>=3.4.0
Requires-Dist: papersize>=1.2.0
Provides-Extra: pymupdf
Requires-Dist: PyMuPDF>=1.26.1; extra == "pymupdf"
Dynamic: license-file
